ptmpl/__init__.py
ptmpl/__version__.py
ptmpl/curves.py
ptmpl/entry_points.py
ptmpl/post_install.py
tests/__init__.py
tests/conftest.py
tests/test_curves.py
ptmpl-0.2.3.dist-info/LICENSE
ptmpl-0.2.3.dist-info/METADATA
ptmpl-0.2.3.dist-info/WHEEL
ptmpl-0.2.3.dist-info/entry_points.txt
ptmpl-0.2.3.dist-info/top_level.txt
ptmpl-0.2.3.dist-info/RECORD
